{
    "images": [
        {
            "imgPath": "img/places/cthulhu.jpg",
            "imgLocation": "Sunken City",
            "description": "High Priest of the Elder Gods",
            "date": "-"
        },
        {
            "imgPath": "img/places/azathoth.jpg",
            "imgLocation": "Self-Existing",
            "description": "Creator, Ruler of Outer Gods",
            "date": "-"
        },
        {
            "imgPath": "img/places/nyarlathotep.jpg",
            "imgLocation": "Walks the Earth",
            "description": "Messenger of the Gods",
            "date": "-"
        },
        {
            "imgPath": "img/places/shubniggurath.jpg",
            "imgLocation": "Dreamlands",
            "description": "One of the Great Old Ones",
            "date": "-"
        },
        {
            "imgPath": "img/places/hastur.jpg",
            "imgLocation": "is he? and person,place or thing??",
            "description": "The Unspeakable One",
            "date": "-"
        }        
  ]
}